{
  "id": "near-52w-high-v1",
  "name": "Near 52W High V1",
  "description": "Leadership strategy that tests whether stocks near 52-week highs continue to outperform over the next few sessions.",
  "enabled": true,
  "universe": {
    "source": "watchlist",
    "min_price": 50,
    "min_avg_volume20": 100000
  },
  "entry": {
    "setup_family": "Near 52W High",
    "min_score": 80,
    "entry_price": "next_open"
  },
  "exit": {
    "take_profit_pct": 10,
    "stop_loss_pct": 5,
    "max_hold_sessions": 15,
    "exit_price": "close",
    "same_day_conflict": "stop_first"
  },
  "risk": {
    "capital_per_trade": 50000,
    "max_positions_per_day": 5
  }
}
